Workbook

Sheet Instructions
B2: INSTRUCTIONS FOR AHIL
B3: Purpose | C3: This workbook asks you to produce a monthly NAV series from the MindWealth forward-simulation record. Every other performance metric in this file derives from that one input series. Do not modify any formula cells (black text). Only fill in the yellow INPUT cells.
B5: SHEET GUIDE
B6: Monthly_NAV | C6: Fill the yellow cells with closing NAV each month-end. All returns, Sharpe, CAGR, drawdown derive from your inputs here.
B7: Portfolio_Stats | C7: Auto-calculated summary — Sharpe, CAGR, vol, max drawdown, best/worst month, % positive months. Do not edit.
B8: Daily_Activity | C8: Optional sheet: fill in daily active signal count so we can compute average capital utilisation.
B10: CONSTRUCTION RULES
B11: Starting Capital | C11: Use $10,000,000 as starting NAV on the first signal date.
B12: Equal Weight | C12: Each active position = 1/N of total portfolio NAV, where N = number of active signals on that day.
B13: Rebalancing | C13: On each new signal entry date, rebalance ALL active positions to 1/N equal weight. Trim existing, add new.
B14: Month-End MTM | C14: Value all open positions at closing price on the last trading day of each month.
B15: Compounding | C15: Each month's closing NAV becomes the next month's opening NAV. Do not withdraw or inject capital.
B16: No Leverage | C16: Gross exposure must not exceed 100% of NAV at any time.
B17: No Fees | C17: No management fee, performance fee, slippage, commission, or financing cost applied.
B18: Risk Free Rate | C18: Use 0% as risk-free rate for Sharpe calculation (stated explicitly in presentation).
B20: WHAT WE NEED FROM YOU
B21: 1. Monthly NAV | C21: The closing NAV of the equal-weight portfolio at the last trading day of each month, from first signal date to today.
B22: 2. Daily Active N | C22: For each trading day: how many signals were simultaneously active (optional but useful for utilisation analysis).
B23: 3. Start Date | C23: Confirm the exact date of the first signal ever fired — this is our Sharpe-clock start.

Sheet Monthly_NAV
B1: MINDWEALTH — MONTHLY NAV & RETURN SERIES | Equal-Weight, Unleveraged, Pre-Fees
B2: Yellow cells = Ahil to populate | Black cells = auto-calculated formulas | Risk-free rate = 0% | No leverage, no fees, no slippage
B3: Month (MMM-YY) | C3: Opening NAV ($) | D3: Closing NAV ($) [FILL IN YELLOW] | E3: Monthly Return (%) | F3: Cumulative Return Since Inception (%) | G3: Annualised Return since Inception (CAGR) Since Inception (%) | H3: Monthly P&L ($) | I3: Drawdown From Peak (%) | J3: Peak NAV To Date ($) | K3: Notes | L3: Benchmark Monthly Return (%) | M3: Excess Return (Portfolio - Benchmark) | N3: Months in Drawdown
B4: Jan-24 | C4: 10000000 | D4: 10232272 | E4: =IF(D4="","",IF(C4=0,"",(D4-C4)/C4)) | F4: =IF(D4="","",(D4-$C$4)/$C$4) | G4: =IF(D4="","",(D4/$C$4)^(12/1)-1) | H4: =IF(D4="","",D4-C4) | I4: =IF(D4="","",IF(J4=0,"",(D4-J4)/J4)) | J4: =IF(D4="","",MAX(D4,$C$4)) | L4: 0.015896 | M4: =IF(OR(D4="",L4=""),"",E4-L4) | N4: =IF(D4="","",IF(I4<0,1,0))
B5: Feb-24 | C5: =D4 | D5: 10663618 | E5: =IF(D5="","",IF(C5=0,"",(D5-C5)/C5)) | F5: =IF(D5="","",(D5-$C$4)/$C$4) | G5: =IF(D5="","",(D5/$C$4)^(12/2)-1) | H5: =IF(D5="","",D5-C5) | I5: =IF(D5="","",IF(J5=0,"",(D5-J5)/J5)) | J5: =IF(D5="","",MAX(D5,J4)) | L5: 0.051721 | M5: =IF(OR(D5="",L5=""),"",E5-L5) | N5: =IF(D5="","",IF(I5<0,N4+1,0))
B6: Mar-24 | C6: =D5 | D6: 10803506 | E6: =IF(D6="","",IF(C6=0,"",(D6-C6)/C6)) | F6: =IF(D6="","",(D6-$C$4)/$C$4) | G6: =IF(D6="","",(D6/$C$4)^(12/3)-1) | H6: =IF(D6="","",D6-C6) | I6: =IF(D6="","",IF(J6=0,"",(D6-J6)/J6)) | J6: =IF(D6="","",MAX(D6,J5)) | L6: 0.031019 | M6: =IF(OR(D6="",L6=""),"",E6-L6) | N6: =IF(D6="","",IF(I6<0,N5+1,0))
B7: Apr-24 | C7: =D6 | D7: 10713144 | E7: =IF(D7="","",IF(C7=0,"",(D7-C7)/C7)) | F7: =IF(D7="","",(D7-$C$4)/$C$4) | G7: =IF(D7="","",(D7/$C$4)^(12/4)-1) | H7: =IF(D7="","",D7-C7) | I7: =IF(D7="","",IF(J7=0,"",(D7-J7)/J7)) | J7: =IF(D7="","",MAX(D7,J6)) | L7: -0.041615 | M7: =IF(OR(D7="",L7=""),"",E7-L7) | N7: =IF(D7="","",IF(I7<0,N6+1,0))
B8: May-24 | C8: =D7 | D8: 10876513 | E8: =IF(D8="","",IF(C8=0,"",(D8-C8)/C8)) | F8: =IF(D8="","",(D8-$C$4)/$C$4) | G8: =IF(D8="","",(D8/$C$4)^(12/5)-1) | H8: =IF(D8="","",D8-C8) | I8: =IF(D8="","",IF(J8=0,"",(D8-J8)/J8)) | J8: =IF(D8="","",MAX(D8,J7)) | L8: 0.048021 | M8: =IF(OR(D8="",L8=""),"",E8-L8) | N8: =IF(D8="","",IF(I8<0,N7+1,0))
B9: Jun-24 | C9: =D8 | D9: 11055711 | E9: =IF(D9="","",IF(C9=0,"",(D9-C9)/C9)) | F9: =IF(D9="","",(D9-$C$4)/$C$4) | G9: =IF(D9="","",(D9/$C$4)^(12/6)-1) | H9: =IF(D9="","",D9-C9) | I9: =IF(D9="","",IF(J9=0,"",(D9-J9)/J9)) | J9: =IF(D9="","",MAX(D9,J8)) | L9: 0.03467 | M9: =IF(OR(D9="",L9=""),"",E9-L9) | N9: =IF(D9="","",IF(I9<0,N8+1,0))
B10: Jul-24 | C10: =D9 | D10: 11311409 | E10: =IF(D10="","",IF(C10=0,"",(D10-C10)/C10)) | F10: =IF(D10="","",(D10-$C$4)/$C$4) | G10: =IF(D10="","",(D10/$C$4)^(12/7)-1) | H10: =IF(D10="","",D10-C10) | I10: =IF(D10="","",IF(J10=0,"",(D10-J10)/J10)) | J10: =IF(D10="","",MAX(D10,J9)) | L10: 0.011321 | M10: =IF(OR(D10="",L10=""),"",E10-L10) | N10: =IF(D10="","",IF(I10<0,N9+1,0))
B11: Aug-24 | C11: =D10 | D11: 11551239 | E11: =IF(D11="","",IF(C11=0,"",(D11-C11)/C11)) | F11: =IF(D11="","",(D11-$C$4)/$C$4) | G11: =IF(D11="","",(D11/$C$4)^(12/8)-1) | H11: =IF(D11="","",D11-C11) | I11: =IF(D11="","",IF(J11=0,"",(D11-J11)/J11)) | J11: =IF(D11="","",MAX(D11,J10)) | L11: 0.022835 | M11: =IF(OR(D11="",L11=""),"",E11-L11) | N11: =IF(D11="","",IF(I11<0,N10+1,0))
B12: Sep-24 | C12: =D11 | D12: 11779811 | E12: =IF(D12="","",IF(C12=0,"",(D12-C12)/C12)) | F12: =IF(D12="","",(D12-$C$4)/$C$4) | G12: =IF(D12="","",(D12/$C$4)^(12/9)-1) | H12: =IF(D12="","",D12-C12) | I12: =IF(D12="","",IF(J12=0,"",(D12-J12)/J12)) | J12: =IF(D12="","",MAX(D12,J11)) | L12: 0.020197 | M12: =IF(OR(D12="",L12=""),"",E12-L12) | N12: =IF(D12="","",IF(I12<0,N11+1,0))
B13: Oct-24 | C13: =D12 | D13: 11735187 | E13: =IF(D13="","",IF(C13=0,"",(D13-C13)/C13)) | F13: =IF(D13="","",(D13-$C$4)/$C$4) | G13: =IF(D13="","",(D13/$C$4)^(12/10)-1) | H13: =IF(D13="","",D13-C13) | I13: =IF(D13="","",IF(J13=0,"",(D13-J13)/J13)) | J13: =IF(D13="","",MAX(D13,J12)) | L13: -0.009897 | M13: =IF(OR(D13="",L13=""),"",E13-L13) | N13: =IF(D13="","",IF(I13<0,N12+1,0))
B14: Nov-24 | C14: =D13 | D14: 12071891 | E14: =IF(D14="","",IF(C14=0,"",(D14-C14)/C14)) | F14: =IF(D14="","",(D14-$C$4)/$C$4) | G14: =IF(D14="","",(D14/$C$4)^(12/11)-1) | H14: =IF(D14="","",D14-C14) | I14: =IF(D14="","",IF(J14=0,"",(D14-J14)/J14)) | J14: =IF(D14="","",MAX(D14,J13)) | L14: 0.057301 | M14: =IF(OR(D14="",L14=""),"",E14-L14) | N14: =IF(D14="","",IF(I14<0,N13+1,0))
B15: Dec-24 | C15: =D14 | D15: 11853505 | E15: =IF(D15="","",IF(C15=0,"",(D15-C15)/C15)) | F15: =IF(D15="","",(D15-$C$4)/$C$4) | G15: =IF(D15="","",(D15/$C$4)^(12/12)-1) | H15: =IF(D15="","",D15-C15) | I15: =IF(D15="","",IF(J15=0,"",(D15-J15)/J15)) | J15: =IF(D15="","",MAX(D15,J14)) | L15: -0.02499 | M15: =IF(OR(D15="",L15=""),"",E15-L15) | N15: =IF(D15="","",IF(I15<0,N14+1,0))
B16: Jan-25 | C16: =D15 | D16: 12208339 | E16: =IF(D16="","",IF(C16=0,"",(D16-C16)/C16)) | F16: =IF(D16="","",(D16-$C$4)/$C$4) | G16: =IF(D16="","",(D16/$C$4)^(12/13)-1) | H16: =IF(D16="","",D16-C16) | I16: =IF(D16="","",IF(J16=0,"",(D16-J16)/J16)) | J16: =IF(D16="","",MAX(D16,J15)) | L16: 0.027016 | M16: =IF(OR(D16="",L16=""),"",E16-L16) | N16: =IF(D16="","",IF(I16<0,N15+1,0))
B17: Feb-25 | C17: =D16 | D17: 12130138 | E17: =IF(D17="","",IF(C17=0,"",(D17-C17)/C17)) | F17: =IF(D17="","",(D17-$C$4)/$C$4) | G17: =IF(D17="","",(D17/$C$4)^(12/14)-1) | H17: =IF(D17="","",D17-C17) | I17: =IF(D17="","",IF(J17=0,"",(D17-J17)/J17)) | J17: =IF(D17="","",MAX(D17,J16)) | L17: -0.014242 | M17: =IF(OR(D17="",L17=""),"",E17-L17) | N17: =IF(D17="","",IF(I17<0,N16+1,0))
B18: Mar-25 | C18: =D17 | D18: 11724473 | E18: =IF(D18="","",IF(C18=0,"",(D18-C18)/C18)) | F18: =IF(D18="","",(D18-$C$4)/$C$4) | G18: =IF(D18="","",(D18/$C$4)^(12/15)-1) | H18: =IF(D18="","",D18-C18) | I18: =IF(D18="","",IF(J18=0,"",(D18-J18)/J18)) | J18: =IF(D18="","",MAX(D18,J17)) | L18: -0.057545 | M18: =IF(OR(D18="",L18=""),"",E18-L18) | N18: =IF(D18="","",IF(I18<0,N17+1,0))
B19: Apr-25 | C19: =D18 | D19: 11711193 | E19: =IF(D19="","",IF(C19=0,"",(D19-C19)/C19)) | F19: =IF(D19="","",(D19-$C$4)/$C$4) | G19: =IF(D19="","",(D19/$C$4)^(12/16)-1) | H19: =IF(D19="","",D19-C19) | I19: =IF(D19="","",IF(J19=0,"",(D19-J19)/J19)) | J19: =IF(D19="","",MAX(D19,J18)) | L19: -0.007625 | M19: =IF(OR(D19="",L19=""),"",E19-L19) | N19: =IF(D19="","",IF(I19<0,N18+1,0))
B20: May-25 | C20: =D19 | D20: 12447562 | E20: =IF(D20="","",IF(C20=0,"",(D20-C20)/C20)) | F20: =IF(D20="","",(D20-$C$4)/$C$4) | G20: =IF(D20="","",(D20/$C$4)^(12/17)-1) | H20: =IF(D20="","",D20-C20) | I20: =IF(D20="","",IF(J20=0,"",(D20-J20)/J20)) | J20: =IF(D20="","",MAX(D20,J19)) | L20: 0.061524 | M20: =IF(OR(D20="",L20=""),"",E20-L20) | N20: =IF(D20="","",IF(I20<0,N19+1,0))
B21: Jun-25 | C21: =D20 | D21: 12834213 | E21: =IF(D21="","",IF(C21=0,"",(D21-C21)/C21)) | F21: =IF(D21="","",(D21-$C$4)/$C$4) | G21: =IF(D21="","",(D21/$C$4)^(12/18)-1) | H21: =IF(D21="","",D21-C21) | I21: =IF(D21="","",IF(J21=0,"",(D21-J21)/J21)) | J21: =IF(D21="","",MAX(D21,J20)) | L21: 0.049607 | M21: =IF(OR(D21="",L21=""),"",E21-L21) | N21: =IF(D21="","",IF(I21<0,N20+1,0))
B22: Jul-25 | C22: =D21 | D22: 12719648 | E22: =IF(D22="","",IF(C22=0,"",(D22-C22)/C22)) | F22: =IF(D22="","",(D22-$C$4)/$C$4) | G22: =IF(D22="","",(D22/$C$4)^(12/19)-1) | H22: =IF(D22="","",D22-C22) | I22: =IF(D22="","",IF(J22=0,"",(D22-J22)/J22)) | J22: =IF(D22="","",MAX(D22,J21)) | L22: 0.021667 | M22: =IF(OR(D22="",L22=""),"",E22-L22) | N22: =IF(D22="","",IF(I22<0,N21+1,0))
B23: Aug-25 | C23: =D22 | D23: 13085015 | E23: =IF(D23="","",IF(C23=0,"",(D23-C23)/C23)) | F23: =IF(D23="","",(D23-$C$4)/$C$4) | G23: =IF(D23="","",(D23/$C$4)^(12/20)-1) | H23: =IF(D23="","",D23-C23) | I23: =IF(D23="","",IF(J23=0,"",(D23-J23)/J23)) | J23: =IF(D23="","",MAX(D23,J22)) | L23: 0.019066 | M23: =IF(OR(D23="",L23=""),"",E23-L23) | N23: =IF(D23="","",IF(I23<0,N22+1,0))
B24: Sep-25 | C24: =D23 | D24: 13305024 | E24: =IF(D24="","",IF(C24=0,"",(D24-C24)/C24)) | F24: =IF(D24="","",(D24-$C$4)/$C$4) | G24: =IF(D24="","",(D24/$C$4)^(12/21)-1) | H24: =IF(D24="","",D24-C24) | I24: =IF(D24="","",IF(J24=0,"",(D24-J24)/J24)) | J24: =IF(D24="","",MAX(D24,J23)) | L24: 0.035324 | M24: =IF(OR(D24="",L24=""),"",E24-L24) | N24: =IF(D24="","",IF(I24<0,N23+1,0))
B25: Oct-25 | C25: =D24 | D25: 13498926 | E25: =IF(D25="","",IF(C25=0,"",(D25-C25)/C25)) | F25: =IF(D25="","",(D25-$C$4)/$C$4) | G25: =IF(D25="","",(D25/$C$4)^(12/22)-1) | H25: =IF(D25="","",D25-C25) | I25: =IF(D25="","",IF(J25=0,"",(D25-J25)/J25)) | J25: =IF(D25="","",MAX(D25,J24)) | L25: 0.022687 | M25: =IF(OR(D25="",L25=""),"",E25-L25) | N25: =IF(D25="","",IF(I25<0,N24+1,0))
B26: Nov-25 | C26: =D25 | D26: 13681077 | E26: =IF(D26="","",IF(C26=0,"",(D26-C26)/C26)) | F26: =IF(D26="","",(D26-$C$4)/$C$4) | G26: =IF(D26="","",(D26/$C$4)^(12/23)-1) | H26: =IF(D26="","",D26-C26) | I26: =IF(D26="","",IF(J26=0,"",(D26-J26)/J26)) | J26: =IF(D26="","",MAX(D26,J25)) | L26: 0.0013 | M26: =IF(OR(D26="",L26=""),"",E26-L26) | N26: =IF(D26="","",IF(I26<0,N25+1,0))
B27: Dec-25 | C27: =D26 | D27: 13724278 | E27: =IF(D27="","",IF(C27=0,"",(D27-C27)/C27)) | F27: =IF(D27="","",(D27-$C$4)/$C$4) | G27: =IF(D27="","",(D27/$C$4)^(12/24)-1) | H27: =IF(D27="","",D27-C27) | I27: =IF(D27="","",IF(J27=0,"",(D27-J27)/J27)) | J27: =IF(D27="","",MAX(D27,J26)) | L27: -0.000524 | M27: =IF(OR(D27="",L27=""),"",E27-L27) | N27: =IF(D27="","",IF(I27<0,N26+1,0))
B28: Jan-26 | C28: =D27 | D28: 13728852 | E28: =IF(D28="","",IF(C28=0,"",(D28-C28)/C28)) | F28: =IF(D28="","",(D28-$C$4)/$C$4) | G28: =IF(D28="","",(D28/$C$4)^(12/25)-1) | H28: =IF(D28="","",D28-C28) | I28: =IF(D28="","",IF(J28=0,"",(D28-J28)/J28)) | J28: =IF(D28="","",MAX(D28,J27)) | L28: 0.013663 | M28: =IF(OR(D28="",L28=""),"",E28-L28) | N28: =IF(D28="","",IF(I28<0,N27+1,0))
B29: Feb-26 | C29: =D28 | D29: 13594084 | E29: =IF(D29="","",IF(C29=0,"",(D29-C29)/C29)) | F29: =IF(D29="","",(D29-$C$4)/$C$4) | G29: =IF(D29="","",(D29/$C$4)^(12/26)-1) | H29: =IF(D29="","",D29-C29) | I29: =IF(D29="","",IF(J29=0,"",(D29-J29)/J29)) | J29: =IF(D29="","",MAX(D29,J28)) | L29: -0.008668 | M29: =IF(OR(D29="",L29=""),"",E29-L29) | N29: =IF(D29="","",IF(I29<0,N28+1,0))
B30: Mar-26 | C30: =D29 | D30: 12972502 | E30: =IF(D30="","",IF(C30=0,"",(D30-C30)/C30)) | F30: =IF(D30="","",(D30-$C$4)/$C$4) | G30: =IF(D30="","",(D30/$C$4)^(12/27)-1) | H30: =IF(D30="","",D30-C30) | I30: =IF(D30="","",IF(J30=0,"",(D30-J30)/J30)) | J30: =IF(D30="","",MAX(D30,J29)) | L30: -0.050933 | M30: =IF(OR(D30="",L30=""),"",E30-L30) | N30: =IF(D30="","",IF(I30<0,N29+1,0))
B31: Apr-26 | C31: =D30 | D31: 13584085 | E31: =IF(D31="","",IF(C31=0,"",(D31-C31)/C31)) | F31: =IF(D31="","",(D31-$C$4)/$C$4) | G31: =IF(D31="","",(D31/$C$4)^(12/28)-1) | H31: =IF(D31="","",D31-C31) | I31: =IF(D31="","",IF(J31=0,"",(D31-J31)/J31)) | J31: =IF(D31="","",MAX(D31,J30)) | L31: 0.104233 | M31: =IF(OR(D31="",L31=""),"",E31-L31) | N31: =IF(D31="","",IF(I31<0,N30+1,0))
B32: May-26 | C32: =D31 | D32: 13914979 | E32: =IF(D32="","",IF(C32=0,"",(D32-C32)/C32)) | F32: =IF(D32="","",(D32-$C$4)/$C$4) | G32: =IF(D32="","",(D32/$C$4)^(12/29)-1) | H32: =IF(D32="","",D32-C32) | I32: =IF(D32="","",IF(J32=0,"",(D32-J32)/J32)) | J32: =IF(D32="","",MAX(D32,J31)) | L32: 0.05147 | M32: =IF(OR(D32="",L32=""),"",E32-L32) | N32: =IF(D32="","",IF(I32<0,N31+1,0))
B33: Jun-26 | C33: =D32 | D33: 13843838 | E33: =IF(D33="","",IF(C33=0,"",(D33-C33)/C33)) | F33: =IF(D33="","",(D33-$C$4)/$C$4) | G33: =IF(D33="","",(D33/$C$4)^(12/30)-1) | H33: =IF(D33="","",D33-C33) | I33: =IF(D33="","",IF(J33=0,"",(D33-J33)/J33)) | J33: =IF(D33="","",MAX(D33,J32)) | L33: -0.010485 | M33: =IF(OR(D33="",L33=""),"",E33-L33) | N33: =IF(D33="","",IF(I33<0,N32+1,0))
B34: Jul-26 | C34: =D33 | E34: =IF(D34="","",IF(C34=0,"",(D34-C34)/C34)) | F34: =IF(D34="","",(D34-$C$4)/$C$4) | G34: =IF(D34="","",(D34/$C$4)^(12/31)-1) | H34: =IF(D34="","",D34-C34) | I34: =IF(D34="","",IF(J34=0,"",(D34-J34)/J34)) | J34: =IF(D34="","",MAX(D34,J33)) | M34: =IF(OR(D34="",L34=""),"",E34-L34) | N34: =IF(D34="","",IF(I34<0,N33+1,0))
B35: Aug-26 | C35: =D34 | E35: =IF(D35="","",IF(C35=0,"",(D35-C35)/C35)) | F35: =IF(D35="","",(D35-$C$4)/$C$4) | G35: =IF(D35="","",(D35/$C$4)^(12/32)-1) | H35: =IF(D35="","",D35-C35) | I35: =IF(D35="","",IF(J35=0,"",(D35-J35)/J35)) | J35: =IF(D35="","",MAX(D35,J34)) | M35: =IF(OR(D35="",L35=""),"",E35-L35) | N35: =IF(D35="","",IF(I35<0,N34+1,0))
B36: Sep-26 | C36: =D35 | E36: =IF(D36="","",IF(C36=0,"",(D36-C36)/C36)) | F36: =IF(D36="","",(D36-$C$4)/$C$4) | G36: =IF(D36="","",(D36/$C$4)^(12/33)-1) | H36: =IF(D36="","",D36-C36) | I36: =IF(D36="","",IF(J36=0,"",(D36-J36)/J36)) | J36: =IF(D36="","",MAX(D36,J35)) | M36: =IF(OR(D36="",L36=""),"",E36-L36) | N36: =IF(D36="","",IF(I36<0,N35+1,0))
B37: Oct-26 | C37: =D36 | E37: =IF(D37="","",IF(C37=0,"",(D37-C37)/C37)) | F37: =IF(D37="","",(D37-$C$4)/$C$4) | G37: =IF(D37="","",(D37/$C$4)^(12/34)-1) | H37: =IF(D37="","",D37-C37) | I37: =IF(D37="","",IF(J37=0,"",(D37-J37)/J37)) | J37: =IF(D37="","",MAX(D37,J36)) | M37: =IF(OR(D37="",L37=""),"",E37-L37) | N37: =IF(D37="","",IF(I37<0,N36+1,0))
B38: Nov-26 | C38: =D37 | E38: =IF(D38="","",IF(C38=0,"",(D38-C38)/C38)) | F38: =IF(D38="","",(D38-$C$4)/$C$4) | G38: =IF(D38="","",(D38/$C$4)^(12/35)-1) | H38: =IF(D38="","",D38-C38) | I38: =IF(D38="","",IF(J38=0,"",(D38-J38)/J38)) | J38: =IF(D38="","",MAX(D38,J37)) | M38: =IF(OR(D38="",L38=""),"",E38-L38) | N38: =IF(D38="","",IF(I38<0,N37+1,0))
B39: Dec-26 | C39: =D38 | E39: =IF(D39="","",IF(C39=0,"",(D39-C39)/C39)) | F39: =IF(D39="","",(D39-$C$4)/$C$4) | G39: =IF(D39="","",(D39/$C$4)^(12/36)-1) | H39: =IF(D39="","",D39-C39) | I39: =IF(D39="","",IF(J39=0,"",(D39-J39)/J39)) | J39: =IF(D39="","",MAX(D39,J38)) | M39: =IF(OR(D39="",L39=""),"",E39-L39) | N39: =IF(D39="","",IF(I39<0,N38+1,0))

Sheet Portfolio_Stats
B1: MINDWEALTH — PORTFOLIO PERFORMANCE STATISTICS (auto-calculated — do not edit)
B2: RETURN METRICS
B3: Total Months of Data | C3: =COUNTA(Monthly_NAV!D4:D39) | D3: Count of months with closing NAV populated
B4: Inception Date (Sharpe-clock start) | C4: 45292 | D4: First trading day of first active signal
B5: Annualised Return (CAGR, since inception) | C5: 0.1389 | D5: Rolling CAGR at latest populated month
B6: Cumulative Return since Inception | C6: =IFERROR(INDEX(Monthly_NAV!F4:F39,COUNTA(Monthly_NAV!D4:D39)),"") | D6: Total % gain from start NAV to latest closing NAV
B7: Best Monthly Return | C7: =IFERROR(MAX(Monthly_NAV!E4:E39),"") | D7: Highest single month return
B8: Worst Monthly Return | C8: =IFERROR(MIN(Monthly_NAV!E4:E39),"") | D8: Worst single month return
B9: % Positive Months | C9: =IFERROR(COUNTIF(Monthly_NAV!E4:E39,">0")/COUNTA(Monthly_NAV!E4:E39),"") | D9: Proportion of months with positive return
B10: Average Monthly Return | C10: =IFERROR(AVERAGEIF(Monthly_NAV!E4:E39,"<>"),"") | D10: Simple average of all monthly returns
B12: RISK METRICS
B13: Annualised Volatility (monthly returns × √12) | C13: =IFERROR(STDEV(Monthly_NAV!E4:E39)*SQRT(12),"") | D13: Std dev of monthly returns annualised
B14: Maximum Drawdown | C14: =IFERROR(MIN(Monthly_NAV!I4:I39),"") | D14: Largest peak-to-trough decline
B15: Sharpe Ratio (risk-free = 0%) | C15: =IFERROR(AVERAGEIF(Monthly_NAV!E4:E39,"<>")*12/(STDEV(Monthly_NAV!E4:E39)*SQRT(12)),"") | D15: Annualised return ÷ annualised vol. Risk-free rate = 0%.
B16: Information Ratio (vs S&P 500) | C16: =IFERROR(AVERAGE(Monthly_NAV!M4:M39)*12/(STDEV(Monthly_NAV!M4:M39)*SQRT(12)),"") | D16: Annualised excess return over S&P 500 / tracking error. Net-long book (NOT market-neutral).
B17: Calmar Ratio (CAGR ÷ Max Drawdown) | C17: =IFERROR(INDEX(Monthly_NAV!G4:G39,COUNTA(Monthly_NAV!D4:D39))/ABS(MIN(Monthly_NAV!I4:I39)),"") | D17: Higher = better return per unit of max drawdown risk
B19: PRESENTATION NOTES
B20: Leverage | C20: None — gross exposure ≤ 100% | D20: State explicitly in all presentations
B21: Fees | C21: None applied in simulation | D21: Virtual forward simulation — state explicitly
B22: Slippage / Commission | C22: None applied | D22: Real-world implementation would reduce returns
B23: Benchmark | C23: S&P 500 (net-long book, ~+$80 net on $100 gross) | D23: Benchmarked to the S&P 500; the book is net long, not market-neutral.
B24: Risk-Free Rate | C24: 0% (stated explicitly) | D24: Conservative — no inflation of Sharpe via negative rates
B25: Record Type | C25: Out-of-sample forward simulation | D25: Signals generated in real-time, not retrospectively adjusted
B26: Equal Weight Method | C26: 1/N per active signal, rebalanced on each new entry | D26: No optimisation, no conviction weighting in Layer 1
B28: Max Drawdown Duration (months, peak->trough) | C28: 2 | D28: Worst DD -5.51% : Jan-26 peak -> Mar-26 trough
B29: Recovery Time (months, trough->new high) | C29: 2 | D29: Months from trough back to prior high-water mark
B31: Version | C31: Version B (all / MTM)
B32: TRUE Daily Max Drawdown (peak->trough) | C32: -0.1326 | D32: Daily peak-to-trough (month-end DD above UNDERSTATES this)

Sheet Daily_Activity
B1: DAILY ACTIVE SIGNALS | Optional — fill if available | Used for capital utilisation analysis
B2: Date | C2: Active Signals (N) [FILL YELLOW] | D2: Capital per Signal = $10m / N | E2: % Portfolio Deployed = N / Max_N × 100% | F2: Notes | H2: SUMMARY STATS
B3: 45292 | C3: 3 | D3: =IF(C3="","",IF(C3=0,"",10000000/C3)) | E3: =IF(C3="","",C3/630) | H3: Average Active Signals (N) | I3: =IFERROR(AVERAGEIF(C3:C901,">0"),"")
B4: 45293 | C4: 3 | D4: =IF(C4="","",IF(C4=0,"",10000000/C4)) | E4: =IF(C4="","",C4/630) | H4: Median Active Signals (N) | I4: =IFERROR(MEDIAN(C3:C901),"")
B5: 45294 | C5: 5 | D5: =IF(C5="","",IF(C5=0,"",10000000/C5)) | E5: =IF(C5="","",C5/630) | H5: Min Active Signals (N) | I5: =IFERROR(MIN(IF(C3:C901>0,C3:C901)),"")
B6: 45295 | C6: 5 | D6: =IF(C6="","",IF(C6=0,"",10000000/C6)) | E6: =IF(C6="","",C6/630) | H6: Max Active Signals (N) | I6: =IFERROR(MAX(C3:C901),"")
B7: 45296 | C7: 6 | D7: =IF(C7="","",IF(C7=0,"",10000000/C7)) | E7: =IF(C7="","",C7/630) | H7: Avg % Portfolio Deployed | I7: =IFERROR(AVERAGEIF(E3:E901,">0"),"")
B8: 45297 | C8: 6 | D8: =IF(C8="","",IF(C8=0,"",10000000/C8)) | E8: =IF(C8="","",C8/630)
B9: 45298 | C9: 13 | D9: =IF(C9="","",IF(C9=0,"",10000000/C9)) | E9: =IF(C9="","",C9/630)
B10: 45299 | C10: 13 | D10: =IF(C10="","",IF(C10=0,"",10000000/C10)) | E10: =IF(C10="","",C10/630)
B11: 45300 | C11: 13 | D11: =IF(C11="","",IF(C11=0,"",10000000/C11)) | E11: =IF(C11="","",C11/630)
B12: 45301 | C12: 14 | D12: =IF(C12="","",IF(C12=0,"",10000000/C12)) | E12: =IF(C12="","",C12/630)
B13: 45302 | C13: 14 | D13: =IF(C13="","",IF(C13=0,"",10000000/C13)) | E13: =IF(C13="","",C13/630)
B14: 45303 | C14: 15 | D14: =IF(C14="","",IF(C14=0,"",10000000/C14)) | E14: =IF(C14="","",C14/630)
B15: 45304 | C15: 15 | D15: =IF(C15="","",IF(C15=0,"",10000000/C15)) | E15: =IF(C15="","",C15/630)
B16: 45305 | C16: 17 | D16: =IF(C16="","",IF(C16=0,"",10000000/C16)) | E16: =IF(C16="","",C16/630)
B17: 45306 | C17: 17 | D17: =IF(C17="","",IF(C17=0,"",10000000/C17)) | E17: =IF(C17="","",C17/630)
B18: 45307 | C18: 18 | D18: =IF(C18="","",IF(C18=0,"",10000000/C18)) | E18: =IF(C18="","",C18/630)
B19: 45308 | C19: 18 | D19: =IF(C19="","",IF(C19=0,"",10000000/C19)) | E19: =IF(C19="","",C19/630)
... B901: 46190 | C901: 0 | D901: =IF(C901="","",IF(C901=0,"",10000000/C901)) | E901: =IF(C901="","",C901/630)

Sheet Drawdown_Episodes
A1: DRAWDOWN EPISODES (daily NAV, peak -> trough -> recovery)
A2: peak_date | B2: trough_date | C2: depth_% | D2: peak_to_trough_days | E2: recovery_days | F2: status
A3: 2025-02-19 | B3: 2025-04-08 | C3: -13.26 | D3: 48 | E3: 35 | F3: recovered
A4: 2026-01-12 | B4: 2026-03-30 | C4: -8.97 | D4: 77 | E4: not yet | F4: OPEN
A5: 2024-07-16 | B5: 2024-08-07 | C5: -5.55 | D5: 22 | E5: 9 | F5: recovered
A6: 2025-07-23 | B6: 2025-08-02 | C6: -3.05 | D6: 10 | E6: 20 | F6: recovered
A7: 2024-12-09 | B7: 2025-01-13 | C7: -2.95 | D7: 35 | E7: 10 | F7: recovered
A8: 2024-08-24 | B8: 2024-09-06 | C8: -2.91 | D8: 13 | E8: 13 | F8: recovered
A9: 2025-11-12 | B9: 2025-11-20 | C9: -2.68 | D9: 8 | E9: 8 | F9: recovered
A10: 2024-10-14 | B10: 2024-11-04 | C10: -2.07 | D10: 21 | E10: 21 | F10: recovered
A11: 2024-03-28 | B11: 2024-04-18 | C11: -2.07 | D11: 21 | E11: 25 | F11: recovered
A12: 2025-10-27 | B12: 2025-11-06 | C12: -1.74 | D12: 10 | E12: 6 | F12: recovered
A13: 2025-10-08 | B13: 2025-10-11 | C13: -1.73 | D13: 3 | E13: 15 | F13: recovered
A14: 2025-12-07 | B14: 2025-12-17 | C14: -1.4 | D14: 10 | E14: 6 | F14: recovered
A15: 2025-09-20 | B15: 2025-09-27 | C15: -1.38 | D15: 7 | E15: 4 | F15: recovered
A16: 2024-05-20 | B16: 2024-05-30 | C16: -1.22 | D16: 10 | E16: 6 | F16: recovered
... A71: 2025-10-03 | B71: 2025-10-04 | C71: 0 | D71: 1 | E71: 1 | F71: recovered
